hrjota/__init__.py
hrjota/globals.py
hrjota/hrjota.py
hrjota/utils/__init__.py
hrjota/utils/text.py
hrjota-0.0.7.dist-info/DESCRIPTION.rst
hrjota-0.0.7.dist-info/METADATA
hrjota-0.0.7.dist-info/RECORD
hrjota-0.0.7.dist-info/WHEEL
hrjota-0.0.7.dist-info/entry_points.txt
hrjota-0.0.7.dist-info/metadata.json
hrjota-0.0.7.dist-info/namespace_packages.txt
hrjota-0.0.7.dist-info/top_level.txt
