Metadata-Version: 2.0
Name: hrjota
Version: 0.0.7
Summary: hrjota ecs roller
Home-page: UNKNOWN
Author: Jacobi Petrucciani
Author-email: jacobi@mimirhq.com
License: UNKNOWN
Platform: Any
Classifier: Programming Language :: Python
Classifier: Programming Language :: Python :: 3.5
Classifier: Intended Audience :: Developers
Classifier: Environment :: Console
Requires-Dist: boto3
Requires-Dist: click
